<stg><name>mm2s_Pipeline_VITIS_LOOP_29_1</name>


<trans_list>

<trans id="34" from="1" to="2">
<condition id="-1">
<or_exp><and_exp></and_exp></or_exp>
</condition>
</trans>
</trans_list>



<state_list>

<state id="1" st_id="2">

<operation id="5" st_id="1" stage="1" lat="1">
<core>NULL</core>
<MemPortIdVec></MemPortIdVec>
<condition id="-1">
<or_exp><and_exp></and_exp></or_exp>
</condition>

<Node id="8" bw="31" op_0_bw="32">
<![CDATA[
newFuncRoot:0 %i = alloca i32 1

]]></Node>
<StgValue><ssdm name="i"/></StgValue>
</operation>

<operation id="6" st_id="1" stage="1" lat="1">
<core>NULL</core>
<MemPortIdVec></MemPortIdVec>
<condition id="-1">
<or_exp><and_exp></and_exp></or_exp>
</condition>

<Node id="9" bw="32" op_0_bw="32" op_1_bw="32">
<![CDATA[
newFuncRoot:1 %size_read = read i32 @_ssdm_op_Read.ap_auto.i32, i32 %size

]]></Node>
<StgValue><ssdm name="size_read"/></StgValue>
</operation>

<operation id="7" st_id="1" stage="1" lat="1">
<core>NULL</core>
<MemPortIdVec></MemPortIdVec>
<condition id="-1">
<or_exp><and_exp></and_exp></or_exp>
</condition>

<Node id="10" bw="62" op_0_bw="62" op_1_bw="62">
<![CDATA[
newFuncRoot:2 %sext_ln29_read = read i62 @_ssdm_op_Read.ap_auto.i62, i62 %sext_ln29

]]></Node>
<StgValue><ssdm name="sext_ln29_read"/></StgValue>
</operation>

<operation id="8" st_id="1" stage="1" lat="1">
<core>NULL</core>
<MemPortIdVec></MemPortIdVec>
<condition id="-1">
<or_exp><and_exp></and_exp></or_exp>
</condition>

<Node id="11" bw="64" op_0_bw="62">
<![CDATA[
newFuncRoot:3 %sext_ln29_cast = sext i62 %sext_ln29_read

]]></Node>
<StgValue><ssdm name="sext_ln29_cast"/></StgValue>
</operation>

<operation id="9" st_id="1" stage="1" lat="1">
<core>NULL</core>
<MemPortIdVec></MemPortIdVec>
<condition id="-1">
<or_exp><and_exp></and_exp></or_exp>
</condition>

<Node id="12" bw="0" op_0_bw="0" op_1_bw="32" op_2_bw="4" op_3_bw="4" op_4_bw="1" op_5_bw="1" op_6_bw="1" op_7_bw="1" op_8_bw="0">
<![CDATA[
newFuncRoot:4 %specaxissidechannel_ln0 = specaxissidechannel void @_ssdm_op_SpecAXISSideChannel, i32 %s_V_data_V, i4 %s_V_keep_V, i4 %s_V_strb_V, i1 0, i1 %s_V_last_V, i1 0, i1 0, void @empty_7

]]></Node>
<StgValue><ssdm name="specaxissidechannel_ln0"/></StgValue>
</operation>

<operation id="10" st_id="1" stage="1" lat="1">
<core>NULL</core>
<MemPortIdVec></MemPortIdVec>
<condition id="-1">
<or_exp><and_exp></and_exp></or_exp>
</condition>

<Node id="13" bw="0" op_0_bw="0" op_1_bw="1" op_2_bw="4" op_3_bw="4" op_4_bw="32" op_5_bw="0" op_6_bw="32" op_7_bw="32" op_8_bw="0" op_9_bw="32" op_10_bw="32" op_11_bw="0" op_12_bw="0" op_13_bw="0" op_14_bw="32" op_15_bw="32" op_16_bw="32" op_17_bw="32" op_18_bw="0" op_19_bw="0" op_20_bw="32" op_21_bw="32">
<![CDATA[
newFuncRoot:5 %specinterface_ln0 = specinterface void @_ssdm_op_SpecInterface, i1 %s_V_last_V, i4 %s_V_strb_V, i4 %s_V_keep_V, i32 %s_V_data_V, void @empty_12, i32 0, i32 0, void @empty_13, i32 0, i32 0, void @empty_3, void @empty_3, void @empty_3, i32 0, i32 0, i32 0, i32 0, void @empty_3, void @empty_3, i32 4294967295, i32 0

]]></Node>
<StgValue><ssdm name="specinterface_ln0"/></StgValue>
</operation>

<operation id="11" st_id="1" stage="1" lat="1">
<core>NULL</core>
<MemPortIdVec></MemPortIdVec>
<condition id="-1">
<or_exp><and_exp></and_exp></or_exp>
</condition>

<Node id="14" bw="0" op_0_bw="0" op_1_bw="32" op_2_bw="0" op_3_bw="32" op_4_bw="32" op_5_bw="0" op_6_bw="32" op_7_bw="32" op_8_bw="0" op_9_bw="0" op_10_bw="0" op_11_bw="32" op_12_bw="32" op_13_bw="32" op_14_bw="32" op_15_bw="0" op_16_bw="0" op_17_bw="32" op_18_bw="32">
<![CDATA[
newFuncRoot:6 %specinterface_ln0 = specinterface void @_ssdm_op_SpecInterface, i32 %gmem, void @empty_2, i32 0, i32 0, void @empty_3, i32 64, i32 0, void @empty_4, void @empty_5, void @empty_3, i32 16, i32 16, i32 16, i32 16, void @empty_3, void @empty_3, i32 4294967295, i32 0

]]></Node>
<StgValue><ssdm name="specinterface_ln0"/></StgValue>
</operation>

<operation id="12" st_id="1" stage="1" lat="1">
<core>NULL</core>
<MemPortIdVec></MemPortIdVec>
<condition id="-1">
<or_exp><and_exp></and_exp></or_exp>
</condition>

<Node id="15" bw="0" op_0_bw="31" op_1_bw="31">
<![CDATA[
newFuncRoot:7 %store_ln0 = store i31 0, i31 %i

]]></Node>
<StgValue><ssdm name="store_ln0"/></StgValue>
</operation>

<operation id="13" st_id="1" stage="1" lat="1">
<core>NULL</core>
<MemPortIdVec></MemPortIdVec>
<condition id="-1">
<or_exp><and_exp></and_exp></or_exp>
</condition>

<Node id="16" bw="0" op_0_bw="0">
<![CDATA[
newFuncRoot:8 %br_ln0 = br void %for.inc

]]></Node>
<StgValue><ssdm name="br_ln0"/></StgValue>
</operation>

<operation id="14" st_id="1" stage="1" lat="1">
<core>NULL</core>
<MemPortIdVec></MemPortIdVec>
<condition id="-1">
<or_exp><and_exp></and_exp></or_exp>
</condition>

<Node id="18" bw="31" op_0_bw="31" op_1_bw="0">
<![CDATA[
for.inc:0 %i_load = load i31 %i

]]></Node>
<StgValue><ssdm name="i_load"/></StgValue>
</operation>

<operation id="15" st_id="1" stage="1" lat="1">
<core>Adder</core>
<MemPortIdVec></MemPortIdVec>
<condition id="-1">
<or_exp><and_exp></and_exp></or_exp>
</condition>

<Node id="19" bw="31" op_0_bw="31" op_1_bw="31">
<![CDATA[
for.inc:1 %add_ln29 = add i31 %i_load, i31 1

]]></Node>
<StgValue><ssdm name="add_ln29"/></StgValue>
</operation>

<operation id="16" st_id="1" stage="1" lat="1">
<core>NULL</core>
<MemPortIdVec></MemPortIdVec>
<condition id="-1">
<or_exp><and_exp></and_exp></or_exp>
</condition>

<Node id="20" bw="32" op_0_bw="31">
<![CDATA[
for.inc:2 %i_cast = zext i31 %i_load

]]></Node>
<StgValue><ssdm name="i_cast"/></StgValue>
</operation>

<operation id="17" st_id="1" stage="1" lat="1">
<core>Cmp</core>
<MemPortIdVec></MemPortIdVec>
<condition id="-1">
<or_exp><and_exp></and_exp></or_exp>
</condition>

<Node id="23" bw="1" op_0_bw="32" op_1_bw="32">
<![CDATA[
for.inc:5 %icmp_ln29 = icmp_slt  i32 %i_cast, i32 %size_read

]]></Node>
<StgValue><ssdm name="icmp_ln29"/></StgValue>
</operation>

<operation id="18" st_id="1" stage="1" lat="1">
<core>NULL</core>
<MemPortIdVec></MemPortIdVec>
<condition id="-1">
<or_exp><and_exp></and_exp></or_exp>
</condition>

<Node id="24" bw="0" op_0_bw="1" op_1_bw="0" op_2_bw="0">
<![CDATA[
for.inc:6 %br_ln29 = br i1 %icmp_ln29, void %for.end.loopexit.exitStub, void %for.inc.split

]]></Node>
<StgValue><ssdm name="br_ln29"/></StgValue>
</operation>

<operation id="19" st_id="1" stage="1" lat="1">
<core>NULL</core>
<MemPortIdVec></MemPortIdVec>
<condition id="-1">
<or_exp><and_exp><literal name="icmp_ln29" val="1"/>
</and_exp></or_exp>
</condition>

<Node id="30" bw="0" op_0_bw="31" op_1_bw="31" op_2_bw="0" op_3_bw="0">
<![CDATA[
for.inc.split:4 %store_ln29 = store i31 %add_ln29, i31 %i

]]></Node>
<StgValue><ssdm name="store_ln29"/></StgValue>
</operation>
</state>

<state id="2" st_id="3">

<operation id="20" st_id="2" stage="1" lat="1">
<core>NULL</core>
<MemPortIdVec></MemPortIdVec>
<condition id="-1">
<or_exp><and_exp></and_exp></or_exp>
</condition>

<Node id="21" bw="0" op_0_bw="0" op_1_bw="32">
<![CDATA[
for.inc:3 %specbitsmap_ln0 = specbitsmap void @_ssdm_op_SpecBitsMap, i32 %gmem

]]></Node>
<StgValue><ssdm name="specbitsmap_ln0"/></StgValue>
</operation>

<operation id="21" st_id="2" stage="1" lat="1">
<core>NULL</core>
<MemPortIdVec></MemPortIdVec>
<condition id="-1">
<or_exp><and_exp></and_exp></or_exp>
</condition>

<Node id="22" bw="32" op_0_bw="32" op_1_bw="64">
<![CDATA[
for.inc:4 %gmem_addr = getelementptr i32 %gmem, i64 %sext_ln29_cast

]]></Node>
<StgValue><ssdm name="gmem_addr"/></StgValue>
</operation>

<operation id="22" st_id="2" stage="1" lat="1">
<core>NULL</core>
<MemPortIdVec></MemPortIdVec>
<condition id="-1">
<or_exp><and_exp><literal name="icmp_ln29" val="1"/>
</and_exp></or_exp>
</condition>

<Node id="26" bw="0" op_0_bw="0" op_1_bw="32" op_2_bw="32" op_3_bw="32" op_4_bw="32" op_5_bw="0">
<![CDATA[
for.inc.split:0 %specpipeline_ln30 = specpipeline void @_ssdm_op_SpecPipeline, i32 1, i32 0, i32 0, i32 0, void @empty_3

]]></Node>
<StgValue><ssdm name="specpipeline_ln30"/></StgValue>
</operation>

<operation id="23" st_id="2" stage="1" lat="1">
<core>NULL</core>
<MemPortIdVec></MemPortIdVec>
<condition id="-1">
<or_exp><and_exp><literal name="icmp_ln29" val="1"/>
</and_exp></or_exp>
</condition>

<Node id="27" bw="0" op_0_bw="0" op_1_bw="0">
<![CDATA[
for.inc.split:1 %specloopname_ln29 = specloopname void @_ssdm_op_SpecLoopName, void @empty_10

]]></Node>
<StgValue><ssdm name="specloopname_ln29"/></StgValue>
</operation>

<operation id="24" st_id="2" stage="1" lat="1">
<core>m_axi</core>
<MemPortIdVec></MemPortIdVec>
<condition id="-1">
<or_exp><and_exp><literal name="icmp_ln29" val="1"/>
</and_exp></or_exp>
</condition>

<Node id="28" bw="32" op_0_bw="32" op_1_bw="32">
<![CDATA[
for.inc.split:2 %x_data_V = read i32 @_ssdm_op_Read.m_axi.p1i32, i32 %gmem_addr

]]></Node>
<StgValue><ssdm name="x_data_V"/></StgValue>
</operation>

<operation id="25" st_id="2" stage="1" lat="1">
<core>axis</core>
<MemPortIdVec></MemPortIdVec>
<condition id="-1">
<or_exp><and_exp><literal name="icmp_ln29" val="1"/>
</and_exp></or_exp>
</condition>

<Node id="29" bw="0" op_0_bw="0" op_1_bw="32" op_2_bw="4" op_3_bw="4" op_4_bw="1" op_5_bw="32" op_6_bw="4" op_7_bw="4" op_8_bw="1">
<![CDATA[
for.inc.split:3 %write_ln258 = write void @_ssdm_op_Write.axis.volatile.i32P0A.i4P0A.i4P0A.i1P0A, i32 %s_V_data_V, i4 %s_V_keep_V, i4 %s_V_strb_V, i1 %s_V_last_V, i32 %x_data_V, i4 15, i4 0, i1 0

]]></Node>
<StgValue><ssdm name="write_ln258"/></StgValue>
</operation>

<operation id="26" st_id="2" stage="1" lat="1">
<core>NULL</core>
<MemPortIdVec></MemPortIdVec>
<condition id="-1">
<or_exp><and_exp><literal name="icmp_ln29" val="1"/>
</and_exp></or_exp>
</condition>

<Node id="31" bw="0" op_0_bw="0">
<![CDATA[
for.inc.split:5 %br_ln29 = br void %for.inc

]]></Node>
<StgValue><ssdm name="br_ln29"/></StgValue>
</operation>

<operation id="27" st_id="2" stage="1" lat="1">
<core>NULL</core>
<MemPortIdVec></MemPortIdVec>
<condition id="-1">
<or_exp><and_exp><literal name="icmp_ln29" val="0"/>
</and_exp></or_exp>
</condition>

<Node id="33" bw="0">
<![CDATA[
for.end.loopexit.exitStub:0 %ret_ln0 = ret

]]></Node>
<StgValue><ssdm name="ret_ln0"/></StgValue>
</operation>
</state>
</state_list>


<ports>
<port id="37" name="gmem" dir="0" iftype="4">
<core>NULL</core><StgValue><ssdm name="gmem"/></StgValue>
</port>
<port id="38" name="sext_ln29" dir="0" iftype="0">
<core>NULL</core><StgValue><ssdm name="sext_ln29"/></StgValue>
</port>
<port id="39" name="size" dir="0" iftype="0">
<core>NULL</core><StgValue><ssdm name="size"/></StgValue>
</port>
<port id="40" name="s_V_data_V" dir="1" iftype="0">
<core>NULL</core><StgValue><ssdm name="s_V_data_V"/></StgValue>
</port>
<port id="41" name="s_V_keep_V" dir="1" iftype="0">
<core>NULL</core><StgValue><ssdm name="s_V_keep_V"/></StgValue>
</port>
<port id="42" name="s_V_strb_V" dir="1" iftype="0">
<core>NULL</core><StgValue><ssdm name="s_V_strb_V"/></StgValue>
</port>
<port id="43" name="s_V_last_V" dir="1" iftype="0">
<core>NULL</core><StgValue><ssdm name="s_V_last_V"/></StgValue>
</port>
</ports>


<dataflows>
<dataflow id="45" from="StgValue_44" to="i" fromId="44" toId="5">
</dataflow>
<dataflow id="47" from="_ssdm_op_Read.ap_auto.i32" to="size_read" fromId="46" toId="6">
</dataflow>
<dataflow id="48" from="size" to="size_read" fromId="39" toId="6">
</dataflow>
<dataflow id="50" from="_ssdm_op_Read.ap_auto.i62" to="sext_ln29_read" fromId="49" toId="7">
</dataflow>
<dataflow id="51" from="sext_ln29" to="sext_ln29_read" fromId="38" toId="7">
</dataflow>
<dataflow id="52" from="sext_ln29_read" to="sext_ln29_cast" fromId="7" toId="8">
</dataflow>
<dataflow id="54" from="_ssdm_op_SpecAXISSideChannel" to="specaxissidechannel_ln0" fromId="53" toId="9">
</dataflow>
<dataflow id="55" from="s_V_data_V" to="specaxissidechannel_ln0" fromId="40" toId="9">
</dataflow>
<dataflow id="56" from="s_V_keep_V" to="specaxissidechannel_ln0" fromId="41" toId="9">
</dataflow>
<dataflow id="57" from="s_V_strb_V" to="specaxissidechannel_ln0" fromId="42" toId="9">
</dataflow>
<dataflow id="59" from="StgValue_58" to="specaxissidechannel_ln0" fromId="58" toId="9">
</dataflow>
<dataflow id="60" from="s_V_last_V" to="specaxissidechannel_ln0" fromId="43" toId="9">
</dataflow>
<dataflow id="61" from="StgValue_58" to="specaxissidechannel_ln0" fromId="58" toId="9">
</dataflow>
<dataflow id="62" from="StgValue_58" to="specaxissidechannel_ln0" fromId="58" toId="9">
</dataflow>
<dataflow id="64" from="empty_7" to="specaxissidechannel_ln0" fromId="63" toId="9">
</dataflow>
<dataflow id="66" from="_ssdm_op_SpecInterface" to="specinterface_ln0" fromId="65" toId="10">
</dataflow>
<dataflow id="67" from="s_V_last_V" to="specinterface_ln0" fromId="43" toId="10">
</dataflow>
<dataflow id="68" from="s_V_strb_V" to="specinterface_ln0" fromId="42" toId="10">
</dataflow>
<dataflow id="69" from="s_V_keep_V" to="specinterface_ln0" fromId="41" toId="10">
</dataflow>
<dataflow id="70" from="s_V_data_V" to="specinterface_ln0" fromId="40" toId="10">
</dataflow>
<dataflow id="72" from="empty_12" to="specinterface_ln0" fromId="71" toId="10">
</dataflow>
<dataflow id="74" from="StgValue_73" to="specinterface_ln0" fromId="73" toId="10">
</dataflow>
<dataflow id="75" from="StgValue_73" to="specinterface_ln0" fromId="73" toId="10">
</dataflow>
<dataflow id="77" from="empty_13" to="specinterface_ln0" fromId="76" toId="10">
</dataflow>
<dataflow id="78" from="StgValue_73" to="specinterface_ln0" fromId="73" toId="10">
</dataflow>
<dataflow id="79" from="StgValue_73" to="specinterface_ln0" fromId="73" toId="10">
</dataflow>
<dataflow id="81" from="empty_3" to="specinterface_ln0" fromId="80" toId="10">
</dataflow>
<dataflow id="82" from="empty_3" to="specinterface_ln0" fromId="80" toId="10">
</dataflow>
<dataflow id="83" from="empty_3" to="specinterface_ln0" fromId="80" toId="10">
</dataflow>
<dataflow id="84" from="StgValue_73" to="specinterface_ln0" fromId="73" toId="10">
</dataflow>
<dataflow id="85" from="StgValue_73" to="specinterface_ln0" fromId="73" toId="10">
</dataflow>
<dataflow id="86" from="StgValue_73" to="specinterface_ln0" fromId="73" toId="10">
</dataflow>
<dataflow id="87" from="StgValue_73" to="specinterface_ln0" fromId="73" toId="10">
</dataflow>
<dataflow id="88" from="empty_3" to="specinterface_ln0" fromId="80" toId="10">
</dataflow>
<dataflow id="89" from="empty_3" to="specinterface_ln0" fromId="80" toId="10">
</dataflow>
<dataflow id="91" from="StgValue_90" to="specinterface_ln0" fromId="90" toId="10">
</dataflow>
<dataflow id="92" from="StgValue_73" to="specinterface_ln0" fromId="73" toId="10">
</dataflow>
<dataflow id="93" from="_ssdm_op_SpecInterface" to="specinterface_ln0" fromId="65" toId="11">
</dataflow>
<dataflow id="94" from="gmem" to="specinterface_ln0" fromId="37" toId="11">
</dataflow>
<dataflow id="96" from="empty_2" to="specinterface_ln0" fromId="95" toId="11">
</dataflow>
<dataflow id="97" from="StgValue_73" to="specinterface_ln0" fromId="73" toId="11">
</dataflow>
<dataflow id="98" from="StgValue_73" to="specinterface_ln0" fromId="73" toId="11">
</dataflow>
<dataflow id="99" from="empty_3" to="specinterface_ln0" fromId="80" toId="11">
</dataflow>
<dataflow id="101" from="StgValue_100" to="specinterface_ln0" fromId="100" toId="11">
</dataflow>
<dataflow id="102" from="StgValue_73" to="specinterface_ln0" fromId="73" toId="11">
</dataflow>
<dataflow id="104" from="empty_4" to="specinterface_ln0" fromId="103" toId="11">
</dataflow>
<dataflow id="106" from="empty_5" to="specinterface_ln0" fromId="105" toId="11">
</dataflow>
<dataflow id="107" from="empty_3" to="specinterface_ln0" fromId="80" toId="11">
</dataflow>
<dataflow id="109" from="StgValue_108" to="specinterface_ln0" fromId="108" toId="11">
</dataflow>
<dataflow id="110" from="StgValue_108" to="specinterface_ln0" fromId="108" toId="11">
</dataflow>
<dataflow id="111" from="StgValue_108" to="specinterface_ln0" fromId="108" toId="11">
</dataflow>
<dataflow id="112" from="StgValue_108" to="specinterface_ln0" fromId="108" toId="11">
</dataflow>
<dataflow id="113" from="empty_3" to="specinterface_ln0" fromId="80" toId="11">
</dataflow>
<dataflow id="114" from="empty_3" to="specinterface_ln0" fromId="80" toId="11">
</dataflow>
<dataflow id="115" from="StgValue_90" to="specinterface_ln0" fromId="90" toId="11">
</dataflow>
<dataflow id="116" from="StgValue_73" to="specinterface_ln0" fromId="73" toId="11">
</dataflow>
<dataflow id="118" from="StgValue_117" to="store_ln0" fromId="117" toId="12">
</dataflow>
<dataflow id="119" from="i" to="store_ln0" fromId="5" toId="12">
</dataflow>
<dataflow id="120" from="i" to="i_load" fromId="5" toId="14">
</dataflow>
<dataflow id="121" from="i_load" to="add_ln29" fromId="14" toId="15">
</dataflow>
<dataflow id="123" from="StgValue_122" to="add_ln29" fromId="122" toId="15">
</dataflow>
<dataflow id="124" from="i_load" to="i_cast" fromId="14" toId="16">
</dataflow>
<dataflow id="125" from="i_cast" to="icmp_ln29" fromId="16" toId="17">
</dataflow>
<dataflow id="126" from="size_read" to="icmp_ln29" fromId="6" toId="17">
</dataflow>
<dataflow id="127" from="icmp_ln29" to="br_ln29" fromId="17" toId="18">
</dataflow>
<dataflow id="128" from="add_ln29" to="store_ln29" fromId="15" toId="19">
</dataflow>
<dataflow id="129" from="i" to="store_ln29" fromId="5" toId="19">
</dataflow>
<dataflow id="131" from="_ssdm_op_SpecBitsMap" to="specbitsmap_ln0" fromId="130" toId="20">
</dataflow>
<dataflow id="132" from="gmem" to="specbitsmap_ln0" fromId="37" toId="20">
</dataflow>
<dataflow id="133" from="gmem" to="gmem_addr" fromId="37" toId="21">
</dataflow>
<dataflow id="134" from="sext_ln29_cast" to="gmem_addr" fromId="8" toId="21">
</dataflow>
<dataflow id="136" from="_ssdm_op_SpecPipeline" to="specpipeline_ln30" fromId="135" toId="22">
</dataflow>
<dataflow id="137" from="StgValue_44" to="specpipeline_ln30" fromId="44" toId="22">
</dataflow>
<dataflow id="138" from="StgValue_73" to="specpipeline_ln30" fromId="73" toId="22">
</dataflow>
<dataflow id="139" from="StgValue_73" to="specpipeline_ln30" fromId="73" toId="22">
</dataflow>
<dataflow id="140" from="StgValue_73" to="specpipeline_ln30" fromId="73" toId="22">
</dataflow>
<dataflow id="141" from="empty_3" to="specpipeline_ln30" fromId="80" toId="22">
</dataflow>
<dataflow id="143" from="_ssdm_op_SpecLoopName" to="specloopname_ln29" fromId="142" toId="23">
</dataflow>
<dataflow id="145" from="empty_10" to="specloopname_ln29" fromId="144" toId="23">
</dataflow>
<dataflow id="147" from="_ssdm_op_Read.m_axi.p1i32" to="x_data_V" fromId="146" toId="24">
</dataflow>
<dataflow id="148" from="gmem_addr" to="x_data_V" fromId="21" toId="24">
</dataflow>
<dataflow id="150" from="_ssdm_op_Write.axis.volatile.i32P0A.i4P0A.i4P0A.i1P0A" to="write_ln258" fromId="149" toId="25">
</dataflow>
<dataflow id="151" from="s_V_data_V" to="write_ln258" fromId="40" toId="25">
</dataflow>
<dataflow id="152" from="s_V_keep_V" to="write_ln258" fromId="41" toId="25">
</dataflow>
<dataflow id="153" from="s_V_strb_V" to="write_ln258" fromId="42" toId="25">
</dataflow>
<dataflow id="154" from="s_V_last_V" to="write_ln258" fromId="43" toId="25">
</dataflow>
<dataflow id="155" from="x_data_V" to="write_ln258" fromId="24" toId="25">
</dataflow>
<dataflow id="157" from="StgValue_156" to="write_ln258" fromId="156" toId="25">
</dataflow>
<dataflow id="159" from="StgValue_158" to="write_ln258" fromId="158" toId="25">
</dataflow>
<dataflow id="161" from="StgValue_160" to="write_ln258" fromId="160" toId="25">
</dataflow>
<dataflow id="162" from="icmp_ln29" to="StgValue_2" fromId="17" toId="2">
</dataflow>
<dataflow id="163" from="icmp_ln29" to="StgValue_3" fromId="17" toId="3">
</dataflow>
</dataflows>


</stg>
